src/__init__.py
src/base.py
src/utils.py
test/__init__.py
test/test_base.py
test/test_utils.py
perfutil-0.1.1.dist-info/METADATA
perfutil-0.1.1.dist-info/WHEEL
perfutil-0.1.1.dist-info/top_level.txt
perfutil-0.1.1.dist-info/RECORD
